setup.py
django_onesky/__init__.py
django_onesky/conf.py
django_onesky/process_messages.py
django_onesky/status.py
django_onesky/utils.py
django_onesky/client/__init__.py
django_onesky/client/base.py
django_onesky/client/order.py
django_onesky/client/project.py
django_onesky/client/project_group.py
django_onesky/management/__init__.py
django_onesky/management/commands/__init__.py
django_onesky/management/commands/onesky_makemessages.py
django_onesky_trans.egg-info/PKG-INFO
django_onesky_trans.egg-info/SOURCES.txt
django_onesky_trans.egg-info/dependency_links.txt
django_onesky_trans.egg-info/requires.txt
django_onesky_trans.egg-info/top_level.txt