Metadata-Version: 1.1
Name: django-onesky-trans
Version: 0.1
Summary: OneSky integration for your Django app
Home-page: http://github.com/django-onesky-trans
Author: Bahattin Cinic
Author-email: bahattincinic@gmail.com
License: MIT
Platform: UNKNOWN
Classifier: Programming Language :: Python
Classifier: Programming Language :: Python :: 2.7
Classifier: Programming Language :: Python :: 3.3
Classifier: Programming Language :: Python :: 3.4
Classifier: Topic :: Software Development :: Libraries :: Python Modules
Classifier: Framework :: Django
Classifier: Environment :: Web Environment
Classifier: Operating System :: OS Independent
Classifier: Natural Language :: English
